CHANGES.txt
CONTRIBUTORS.txt
README.txt
TODO.txt
setup.py
docs/INSTALL.txt
docs/LICENSE.GPL
docs/LICENSE.txt
vs/__init__.py
vs.org.egg-info/PKG-INFO
vs.org.egg-info/SOURCES.txt
vs.org.egg-info/dependency_links.txt
vs.org.egg-info/entry_points.txt
vs.org.egg-info/namespace_packages.txt
vs.org.egg-info/not-zip-safe
vs.org.egg-info/paster_plugins.txt
vs.org.egg-info/requires.txt
vs.org.egg-info/top_level.txt
vs/org/TODO.txt
vs/org/__init__.py
vs/org/config.py
vs/org/configure.zcml
vs/org/header.txt
vs/org/setuphandlers.py
vs/org/adapters/__init__.py
vs/org/adapters/addresses.py
vs/org/adapters/configure.zcml
vs/org/adapters/employee_vcard.py
vs/org/adapters/imagesupport.py
vs/org/adapters/indexer.py
vs/org/adapters/keywords.py
vs/org/browser/__init__.py
vs/org/browser/businessareas_for_location.pt
vs/org/browser/configure.zcml
vs/org/browser/department.py
vs/org/browser/department_overview.pt
vs/org/browser/department_view.pt
vs/org/browser/departmentoverview.py
vs/org/browser/departments_for_institution.pt
vs/org/browser/employee.py
vs/org/browser/employee_hcard.pt
vs/org/browser/employee_view.pt
vs/org/browser/employeefolder.py
vs/org/browser/employeefolder_view.pt
vs/org/browser/imagesupport.py
vs/org/browser/institution.py
vs/org/browser/institution_overview.pt
vs/org/browser/institution_view.pt
vs/org/browser/institutionoverview.py
vs/org/browser/institutions_for_location_and_businessarea.pt
vs/org/browser/interfaces.py
vs/org/browser/map.pt
vs/org/browser/maps.js.pt
vs/org/browser/mapsupport.py
vs/org/browser/organisation.pt
vs/org/browser/organisation.py
vs/org/browser/staffsort.py
vs/org/browser/vbbsupport.py
vs/org/browser/vcardsupport.py
vs/org/browser/views.py
vs/org/browser/images/address_icon.gif
vs/org/browser/images/department_icon.gif
vs/org/browser/images/departmentsfolder_icon.gif
vs/org/browser/images/email_icon.gif
vs/org/browser/images/empfang_icon.gif
vs/org/browser/images/employee_icon.gif
vs/org/browser/images/employeefolder_icon.gif
vs/org/browser/images/fax_icon.gif
vs/org/browser/images/group_icon.gif
vs/org/browser/images/homepage_icon.gif
vs/org/browser/images/institution_icon.gif
vs/org/browser/images/link_external_icon.gif
vs/org/browser/images/map_icon.gif
vs/org/browser/images/phone_icon.gif
