Metadata-Version: 1.0
Name: vs.org
Version: 1.1.1
Summary: Plone 4 add-on: Representation of organisational structures
Home-page: http://svn.plone.org/svn/collective/vs.org/
Author: Veit Schiele
Author-email: vs.org@veit-schiele.de
License: GPL
Keywords: Zope Plone
Platform: UNKNOWN
Classifier: Development Status :: 5 - Production/Stable
Classifier: Framework :: Plone
Classifier: Framework :: Plone :: 4.3
Classifier: Programming Language :: Python
Classifier: Topic :: Software Development :: Libraries :: Python Modules
Classifier: License :: OSI Approved :: GNU General Public License (GPL)
